jorun/__init__.py
jorun/configuration.py
jorun/constants.py
jorun/errors.py
jorun/logger.py
jorun/main.py
jorun/runner.py
jorun/runner_process.py
jorun/scanner.py
jorun/utils.py
jorun/handler/__init__.py
jorun/handler/base.py
jorun/handler/docker.py
jorun/handler/group.py
jorun/handler/shell.py
jorun/messaging/__init__.py
jorun/messaging/message.py
jorun/palette/__init__.py
jorun/palette/base.py
jorun/palette/darcula.py
jorun/palette/hacker.py
jorun/palette/kimbie_dark.py
jorun/palette/monokai.py
jorun/palette/solarized_dark.py
jorun/types/__init__.py
jorun/types/options.py
jorun/types/task.py
jorun/ui/__init__.py
jorun/ui/application.py
jorun/ui/command_handler.py
jorun/ui/data_signals.py
jorun/ui/main_window.py
jorun/ui/pane.py
jorun/ui/task_panel.py
jorun/ui/utils.py
jorun-0.2.1.dist-info/METADATA
jorun-0.2.1.dist-info/WHEEL
jorun-0.2.1.dist-info/entry_points.txt
jorun-0.2.1.dist-info/licenses/LICENSE
jorun-0.2.1.dist-info/RECORD
