Metadata-Version: 2.1
Name: jorun
Version: 0.2.1
Summary: A customizable task runner
Project-URL: Homepage, https://github.com/paolo-projects/jorun
Project-URL: Bug Tracker, https://github.com/paolo-projects/jorun/issues
Author-email: Paolo Infante <info@paoloinfante.it>
License-File: LICENSE
Classifier: License :: OSI Approved :: MIT License
Classifier: Operating System :: OS Independent
Classifier: Programming Language :: Python :: 3
Requires-Python: >=3.7
Requires-Dist: psutil==5.9.5
Requires-Dist: pyside6==6.5.0
Requires-Dist: pyyaml==6.0
Requires-Dist: tinyioc==0.1.4
